Metadata-Version: 2.1
Name: aiohttp-apispec-patch
Version: 2.0.0
Summary: Build and document REST APIs with aiohttp and apispec
Home-page: https://github.com/maksimvrs/aiohttp-apispec
Author: Maksim Vorontsov
Author-email: social.maksim.vrs@gmail.com
License: MIT
Keywords: aiohttp marshmallow apispec swagger
Platform: UNKNOWN
Classifier: Development Status :: 5 - Production/Stable
Classifier: Intended Audience :: Developers
Classifier: License :: OSI Approved :: MIT License
Classifier: Natural Language :: English
Classifier: Programming Language :: Python :: 3.5
Classifier: Programming Language :: Python :: 3.6
Classifier: Programming Language :: Python :: 3.7
